pulumi_pulumiservice/__init__.py
pulumi_pulumiservice/_enums.py
pulumi_pulumiservice/_inputs.py
pulumi_pulumiservice/_utilities.py
pulumi_pulumiservice/access_token.py
pulumi_pulumiservice/agent_pool.py
pulumi_pulumiservice/approval_rule.py
pulumi_pulumiservice/deployment_schedule.py
pulumi_pulumiservice/deployment_settings.py
pulumi_pulumiservice/drift_schedule.py
pulumi_pulumiservice/environment.py
pulumi_pulumiservice/environment_rotation_schedule.py
pulumi_pulumiservice/environment_version_tag.py
pulumi_pulumiservice/get_insights_account.py
pulumi_pulumiservice/get_insights_accounts.py
pulumi_pulumiservice/get_policy_pack.py
pulumi_pulumiservice/get_policy_packs.py
pulumi_pulumiservice/insights_account.py
pulumi_pulumiservice/oidc_issuer.py
pulumi_pulumiservice/org_access_token.py
pulumi_pulumiservice/outputs.py
pulumi_pulumiservice/policy_group.py
pulumi_pulumiservice/provider.py
pulumi_pulumiservice/pulumi-plugin.json
pulumi_pulumiservice/py.typed
pulumi_pulumiservice/stack.py
pulumi_pulumiservice/stack_tag.py
pulumi_pulumiservice/team.py
pulumi_pulumiservice/team_access_token.py
pulumi_pulumiservice/team_environment_permission.py
pulumi_pulumiservice/team_stack_permission.py
pulumi_pulumiservice/template_source.py
pulumi_pulumiservice/ttl_schedule.py
pulumi_pulumiservice/webhook.py
pulumi_pulumiservice/config/__init__.py
pulumi_pulumiservice/config/__init__.pyi
pulumi_pulumiservice/config/vars.py
pulumi_pulumiservice-0.34.0.dist-info/METADATA
pulumi_pulumiservice-0.34.0.dist-info/WHEEL
pulumi_pulumiservice-0.34.0.dist-info/top_level.txt
pulumi_pulumiservice-0.34.0.dist-info/RECORD
