Metadata-Version: 2.4
Name: pulumi_pulumiservice
Version: 0.34.0
Summary: A native Pulumi package for creating and managing Pulumi Cloud constructs
License: Apache-2.0
Project-URL: Homepage, https://pulumi.com
Project-URL: Repository, https://github.com/pulumi/pulumi-pulumiservice
Keywords: pulumi,kind/native,category/infrastructure
Requires-Python: >=3.9
Requires-Dist: parver>=0.2.1
Requires-Dist: pulumi<4.0.0,>=3.0.0
Requires-Dist: semver>=2.8.1
Requires-Dist: typing-extensions<5,>=4.11; python_version < "3.11"
